tmp/__init__.py
tmp/main.py
tmp_sample-1.0.0.dist-info/LICENSE
tmp_sample-1.0.0.dist-info/METADATA
tmp_sample-1.0.0.dist-info/WHEEL
tmp_sample-1.0.0.dist-info/top_level.txt
tmp_sample-1.0.0.dist-info/RECORD
