Metadata-Version: 2.1
Name: tmp-sample
Version: 1.0.0
Summary: tmp
Home-page: https://github.com/TorDataScientist/tmp-sample
Author: TorDataScientist
License: MIT License
Platform: UNKNOWN
License-File: LICENSE
